pipeline_components/AbstractSchemaProvider.py
pipeline_components/AbstractStructuredTransform.py
pipeline_components/AutoRunPipeline.py
pipeline_components/PipelineOptionsProvider.py
pipeline_components/PipelineRunnerInterface.py
pipeline_components/__init__.py
pipeline_components/data_cleaning.py
pipeline_components/data_enrichment.py
pipeline_components/data_understand.py
pipeline_components/input_file.py
utils/BigqueryToRaw.py
utils/ParseCsv.py
utils/__init__.py
utils/gcp_utils.py
utils/test_gcp_utils.py
dojo_beam_transforms2-2.0.0.dist-info/METADATA
dojo_beam_transforms2-2.0.0.dist-info/WHEEL
dojo_beam_transforms2-2.0.0.dist-info/top_level.txt
dojo_beam_transforms2-2.0.0.dist-info/RECORD
