Metadata-Version: 2.4
Name: dojo-beam-transforms2
Version: 2.0.0
Requires-Dist: apache-beam[dataframe,gcp,interactive]==2.58.1
Requires-Dist: pandas==2.0.3
Requires-Dist: pandas-datareader==0.10.0
Requires-Dist: PyMuPDF==1.23.22
Requires-Dist: pypinyin==0.51.0
Requires-Dist: unidecode==1.3.8
Requires-Dist: openpyxl==3.0.10
Requires-Dist: fsspec==2024.6.1
Requires-Dist: gcsfs==2024.6.1
Requires-Dist: google-cloud-secret-manager==2.22.0
Dynamic: requires-dist
